
---
ChÆ°Æ¡ng 4 cá»§a **Java Virtual Machine Specification (JVM Spec) SE 21** mÃ´ táº£ Ä‘á»‹nh dáº¡ng cá»§a file **`.class`**, hay cÃ²n gá»i lÃ  **Class File Format**. ÄÃ¢y lÃ  Ä‘á»‹nh dáº¡ng mÃ  mÃ£ Java Ä‘Æ°á»£c biÃªn dá»‹ch thÃ nh trÆ°á»›c khi JVM thá»±c thi.

## ğŸ”¹ 1. Tá»•ng quan vá» Class File Format

Má»™t file `.class` chá»©a **bytecode**, lÃ  táº­p há»£p cÃ¡c lá»‡nh Ä‘Æ°á»£c JVM hiá»ƒu vÃ  thá»±c thi. File nÃ y cÃ³ cáº¥u trÃºc **nhá»‹ phÃ¢n**, khÃ´ng thá»ƒ Ä‘á»c trá»±c tiáº¿p nhÆ° mÃ£ Java.

Má»i file `.class` Ä‘á»u cÃ³ cáº¥u trÃºc theo thá»© tá»± sau:

| ThÃ nh pháº§n        | KÃ­ch thÆ°á»›c | Chá»©c nÄƒng                                                |
| ----------------- | ---------- | -------------------------------------------------------- |
| **Magic Number**  | 4 byte     | XÃ¡c Ä‘á»‹nh Ä‘Ã¢y lÃ  file `.class` há»£p lá»‡                     |
| **Version**       | 4 byte     | PhiÃªn báº£n cá»§a JVM há»— trá»£ file nÃ y                        |
| **Constant Pool** | Biáº¿n Ä‘á»•i   | Báº£ng háº±ng sá»‘ chá»©a thÃ´ng tin tÃªn, kiá»ƒu, giÃ¡ trá»‹, v.v.     |
| **Access Flags**  | 2 byte     | Quyá»n truy cáº­p cá»§a class (public, final, abstract, v.v.) |
| **This Class**    | 2 byte     | Chá»‰ má»¥c cá»§a class hiá»‡n táº¡i trong constant pool           |
| **Super Class**   | 2 byte     | Chá»‰ má»¥c cá»§a class cha trong constant pool                |
| **Interfaces**    | Biáº¿n Ä‘á»•i   | Danh sÃ¡ch cÃ¡c interface mÃ  class nÃ y implement           |
| **Fields**        | Biáº¿n Ä‘á»•i   | Danh sÃ¡ch cÃ¡c thuá»™c tÃ­nh (fields) cá»§a class              |
| **Methods**       | Biáº¿n Ä‘á»•i   | Danh sÃ¡ch cÃ¡c phÆ°Æ¡ng thá»©c (methods) cá»§a class            |
| **Attributes**    | Biáº¿n Ä‘á»•i   | CÃ¡c thÃ´ng tin bá»• sung nhÆ° annotations, generic, v.v.     |
## ğŸ”¹ 2. Chi tiáº¿t tá»«ng thÃ nh pháº§n

### ğŸŸ¢ **Magic Number**

- Má»—i file `.class` báº¯t Ä‘áº§u báº±ng **4 byte cá»‘ Ä‘á»‹nh** cÃ³ giÃ¡ trá»‹ **0xCAFEBABE**.
- Má»¥c Ä‘Ã­ch: GiÃºp JVM nháº­n diá»‡n Ä‘Ã¢y lÃ  file `.class` há»£p lá»‡.
- Náº¿u file khÃ´ng báº¯t Ä‘áº§u báº±ng `CAFEBABE`, JVM sáº½ bÃ¡o lá»—i.

ğŸ“Œ **VÃ­ dá»¥** (hexadecimal format cá»§a file `.class`):
```
CA FE BA BE 00 00 00 37 ...
```
(`00 37` lÃ  phiÃªn báº£n cá»§a JVM â€“ tÆ°Æ¡ng Ä‘Æ°Æ¡ng Java 21)
### ğŸŸ¢ **Version (Major & Minor Version)**

- **4 byte** tiáº¿p theo xÃ¡c Ä‘á»‹nh phiÃªn báº£n cá»§a JVM cÃ³ thá»ƒ cháº¡y file nÃ y.
- **Minor version (2 byte) + Major version (2 byte)**.
- Major version cá»§a cÃ¡c phiÃªn báº£n Java thÃ´ng dá»¥ng:

|Java Version|Major Version|
|---|---|
|Java 8|52|
|Java 11|55|
|Java 17|61|
|Java 21|65|

ğŸ“Œ **VÃ­ dá»¥**: `00 00 00 37` (0x0037 = 55) â†’ file nÃ y Ä‘Æ°á»£c biÃªn dá»‹ch báº±ng **Java 21**. (45->65)

### ğŸŸ¢ **Constant Pool**

- ÄÃ¢y lÃ  pháº§n lá»›n nháº¥t trong file `.class`, chá»©a **háº±ng sá»‘** (tÃªn class, tÃªn method, chuá»—i, sá»‘ nguyÃªn, v.v.).
- Dá»¯ liá»‡u Ä‘Æ°á»£c lÆ°u theo **index** (chá»‰ má»¥c), cÃ¡c thÃ nh pháº§n khÃ¡c trong file `.class` sáº½ tham chiáº¿u Ä‘áº¿n Ä‘Ã¢y.
- CÃ³ nhiá»u loáº¡i entry, má»—i loáº¡i cÃ³ **1 byte tag** Ä‘áº§u tiÃªn Ä‘á»ƒ phÃ¢n loáº¡i.

ğŸ“Œ **VÃ­ dá»¥ cÃ¡c entry trong constant pool:**
```java
CONSTANT_Class      # TÃªn class
CONSTANT_Fieldref   # Tham chiáº¿u field
CONSTANT_Methodref  # Tham chiáº¿u method
CONSTANT_String     # LÆ°u chuá»—i
CONSTANT_Integer    # LÆ°u sá»‘ nguyÃªn
```
ğŸ”¥ **VÃ­ dá»¥ minh há»a** Giáº£ sá»­ chÃºng ta cÃ³ class:
```java
public class Hello {
    public static void main(String[] args) {
        System.out.println("Hello, JVM!");
    }
}
```
ğŸ“Œ Má»™t pháº§n **constant pool** cá»§a file `.class` sáº½ trÃ´ng nhÆ° tháº¿ nÃ y:
```java
#1 = Class          #2         // Hello
#2 = Utf8           Hello
#3 = Methodref      #4.#5      // System.out.println
#4 = Class          #6         // java/lang/System
#5 = NameAndType    #7:#8      // println:(Ljava/lang/String;)V
#6 = Utf8           java/lang/System
#7 = Utf8           println
#8 = Utf8           (Ljava/lang/String;)V
```
- `#1` lÃ  class `Hello`
- `#3` lÃ  method `System.out.println`
- `#8` lÃ  kiá»ƒu dá»¯ liá»‡u `void (String)`

### ğŸŸ¢ **Access Flags**

- **2 byte** xÃ¡c Ä‘á»‹nh **modifier** cá»§a class:
    - `0x0001` â†’ `public`
    - `0x0010` â†’ `final`
    - `0x0020` â†’ `super` (sá»­ dá»¥ng `invokespecial` cho super class)
    - `0x0200` â†’ `interface`
    - `0x0400` â†’ `abstract`
    - `0x1000` â†’ `synthetic` (Ä‘Æ°á»£c táº¡o bá»Ÿi trÃ¬nh biÃªn dá»‹ch)
ğŸ“Œ **VÃ­ dá»¥**:
```java
Access Flags: 0x0021 (public, super)
```
NghÄ©a lÃ  class nÃ y cÃ³ `public` vÃ  `super`.
### ğŸŸ¢ **This Class & Super Class**

- **This Class (2 byte)**: Chá»‰ má»¥c cá»§a class hiá»‡n táº¡i trong constant pool.
- **Super Class (2 byte)**: Chá»‰ má»¥c cá»§a class cha trong constant pool (`Object` náº¿u khÃ´ng káº¿ thá»«a gÃ¬).

ğŸ“Œ **VÃ­ dá»¥**:
```java
This Class: #1 (Hello)
Super Class: #2 (java/lang/Object)
```
### ğŸŸ¢ **Interfaces**

- Náº¿u class implement interface, danh sÃ¡ch cÃ¡c interface Ä‘Æ°á»£c lÆ°u á»Ÿ Ä‘Ã¢y.

ğŸ“Œ **VÃ­ dá»¥**:
```java
public class MyClass implements Runnable {
    @Override
    public void run() {}
}
```
ğŸ“Œ Trong file `.class`:
```java
Interfaces: 1
Interface[0]: #3 (java/lang/Runnable)
```
### ğŸŸ¢ **Fields**

- Danh sÃ¡ch cÃ¡c thuá»™c tÃ­nh (biáº¿n instance/static).
- Má»—i field cÃ³:
    - Access flags (private, public, static, final)
    - Name index (trá» vÃ o constant pool)
    - Descriptor index (kiá»ƒu dá»¯ liá»‡u)
    - Attribute list (annotations, generic, v.v.)
ğŸ“Œ **VÃ­ dá»¥**:
```java
private int count;
```
Trong file `.class`:
```java
Field:
  Name: #5 (count)
  Descriptor: #6 (I)  // I = int
  Flags: 0x0002 (private)
```
### ğŸŸ¢ **Methods**

- Danh sÃ¡ch cÃ¡c phÆ°Æ¡ng thá»©c (methods).
- Cáº¥u trÃºc tÆ°Æ¡ng tá»± nhÆ° fields nhÆ°ng cÃ³ thÃªm **bytecode** trong pháº§n Attributes.

ğŸ“Œ **VÃ­ dá»¥**:
```java
public void print() { System.out.println("Hello"); }
```
Trong file `.class`:
```java
Method:
  Name: #9 (print)
  Descriptor: #10 ()V  // ()V = void print()
  Flags: 0x0001 (public)
  Code:
    aload_0
    invokevirtual #11 (java/lang/System.out.println)
    return
```
### ğŸŸ¢ **Attributes**

- Chá»©a thÃ´ng tin bá»• sung:
    - `Code` (chá»©a bytecode)
    - `LineNumberTable` (map giá»¯a dÃ²ng code Java vÃ  bytecode)
    - `SourceFile` (tÃªn file `.java`)
    - `Annotations`, `Generic`, v.v.
## ğŸ”¥ Káº¿t luáº­n

File `.class` chá»©a **bytecode**, vÃ  JVM Ä‘á»c nÃ³ theo cáº¥u trÃºc cá»¥ thá»ƒ. Hiá»ƒu Class File Format giÃºp báº¡n:

- Debug lá»—i class loading.
- Viáº¿t trÃ¬nh phÃ¢n tÃ­ch file `.class`.
- Hiá»ƒu cÃ¡ch JVM thá»±c thi Java.