
---
ChÆ°Æ¡ng nÃ y mÃ´ táº£ cÃ¡ch mÃ£ nguá»“n Java Ä‘Æ°á»£c biÃªn dá»‹ch thÃ nh bytecode vÃ  cÃ¡ch JVM thá»±c thi bytecode Ä‘Ã³.

## **1ï¸âƒ£ QuÃ¡ trÃ¬nh biÃªn dá»‹ch Java**

QuÃ¡ trÃ¬nh biÃªn dá»‹ch trong Java diá»…n ra nhÆ° sau:

1ï¸âƒ£ **Viáº¿t mÃ£ nguá»“n** (`.java`)  
2ï¸âƒ£ **BiÃªn dá»‹ch** (`javac`) â†’ táº¡o bytecode (`.class`)  
3ï¸âƒ£ **JVM thá»±c thi bytecode** báº±ng **Interpreter** hoáº·c **JIT Compiler**

VÃ­ dá»¥:
```java
public class Example {
    public static void main(String[] args) {
        int x = 5;
        int y = 10;
        int sum = x + y;
        System.out.println("Sum: " + sum);
    }
}
```
MÃ£ trÃªn sáº½ Ä‘Æ°á»£c biÃªn dá»‹ch thÃ nh **bytecode**, cÃ³ thá»ƒ xem báº±ng lá»‡nh:
```sh
javap -c Example.class
```
Káº¿t quáº£ bytecode (giáº£n lÆ°á»£c):
```makefile
0: iconst_5
1: istore_1
2: iconst_10
3: istore_2
4: iload_1
5: iload_2
6: iadd
7: istore_3
8: getstatic java/lang/System.out : Ljava/io/PrintStream;
9: iload_3
10: invokevirtual java/io/PrintStream.println
```
- `iconst_5` â†’ Äáº©y giÃ¡ trá»‹ `5` lÃªn Stack
- `istore_1` â†’ LÆ°u vÃ o biáº¿n `x`
- `iload_1`, `iload_2` â†’ Äá»c giÃ¡ trá»‹ cá»§a `x`, `y`
- `iadd` â†’ Cá»™ng hai sá»‘
- `invokevirtual` â†’ Gá»i `println()`

## **2ï¸âƒ£ Táº¡i sao dÃ¹ng bytecode?**

- **Äá»™c láº­p ná»n táº£ng**: JVM cÃ³ thá»ƒ cháº¡y bytecode trÃªn má»i há»‡ Ä‘iá»u hÃ nh.
- **Tá»‘i Æ°u hÃ³a**: JIT Compiler dá»‹ch bytecode thÃ nh mÃ£ mÃ¡y khi cáº§n.
- **Báº£o máº­t**: JVM kiá»ƒm tra bytecode trÆ°á»›c khi thá»±c thi.

---
### SÃ‚U HÆ N Ná»®A ÄI ANH!!! OK EM

### **QuÃ¡ trÃ¬nh biÃªn dá»‹ch mÃ£ nguá»“n Java thÃ nh bytecode** ğŸš€

QuÃ¡ trÃ¬nh biÃªn dá»‹ch Java gá»“m nhiá»u bÆ°á»›c Ä‘á»ƒ chuyá»ƒn Ä‘á»•i mÃ£ nguá»“n (`.java`) thÃ nh bytecode (`.class`), sau Ä‘Ã³ JVM thá»±c thi bytecode nÃ y. ChÃºng ta sáº½ Ä‘i sÃ¢u vÃ o tá»«ng giai Ä‘oáº¡n.
## **1ï¸âƒ£ CÃ¡c giai Ä‘oáº¡n cá»§a trÃ¬nh biÃªn dá»‹ch Java (`javac`)**

Khi báº¡n cháº¡y lá»‡nh:
`javac Example.java

trÃ¬nh biÃªn dá»‹ch (`javac`) thá»±c hiá»‡n cÃ¡c bÆ°á»›c sau:
### **ğŸ”¹ Giai Ä‘oáº¡n 1: PhÃ¢n tÃ­ch mÃ£ nguá»“n (Lexical Analysis & Parsing)**

TrÃ¬nh biÃªn dá»‹ch **Ä‘á»c mÃ£ nguá»“n** vÃ  tÃ¡ch thÃ nh cÃ¡c **token** (tá»« khÃ³a, toÃ¡n tá»­, biáº¿n, phÆ°Æ¡ng thá»©c, v.v.).

- **Lexical Analysis**: Chia mÃ£ nguá»“n thÃ nh token (sá»­ dá»¥ng bá»™ phÃ¢n tÃ­ch tá»« vá»±ng - Lexer).
- **Parsing**: XÃ¢y dá»±ng cÃ¢y cÃº phÃ¡p trá»«u tÆ°á»£ng (AST - Abstract Syntax Tree) Ä‘á»ƒ kiá»ƒm tra cÃº phÃ¡p.
VÃ­ dá»¥:
```java
int sum = a + b;
```
Lexer sáº½ tÃ¡ch thÃ nh:
```java
[int] [sum] [=] [a] [+] [b] [;]
```
Parser xÃ¢y dá»±ng cÃ¢y AST:
```java
Assignment
 â”œâ”€â”€ Variable: sum
 â”œâ”€â”€ Expression: a + b
```
### **ğŸ”¹ Giai Ä‘oáº¡n 2: Kiá»ƒm tra ngá»¯ nghÄ©a (Semantic Analysis)**

- **Kiá»ƒm tra kiá»ƒu dá»¯ liá»‡u** (`Type Checking`): Äáº£m báº£o biáº¿n `sum` cÃ³ cÃ¹ng kiá»ƒu dá»¯ liá»‡u vá»›i `a + b`.
- **Kiá»ƒm tra pháº¡m vi** (`Scope Checking`): Kiá»ƒm tra `a, b` cÃ³ Ä‘Æ°á»£c khai bÃ¡o trÆ°á»›c khÃ´ng.
- **Kiá»ƒm tra tham chiáº¿u**: Kiá»ƒm tra `sum` cÃ³ thá»ƒ gÃ¡n giÃ¡ trá»‹ khÃ´ng.

Náº¿u cÃ³ lá»—i, trÃ¬nh biÃªn dá»‹ch sáº½ bÃ¡o lá»—i:
`error: cannot find symbol`
### **ğŸ”¹ Giai Ä‘oáº¡n 3: Sinh mÃ£ trung gian (Intermediate Representation - IR)**

Sau khi kiá»ƒm tra xong, trÃ¬nh biÃªn dá»‹ch táº¡o má»™t **Ä‘áº¡i diá»‡n trung gian** cá»§a chÆ°Æ¡ng trÃ¬nh, thÆ°á»ng dÆ°á»›i dáº¡ng **táº­p lá»‡nh 3 Ä‘á»‹a chá»‰ (Three-Address Code - TAC)** hoáº·c **cÃ¢y IR**.

VÃ­ dá»¥, mÃ£ Java:
```java
int sum = a + b;
```
cÃ³ thá»ƒ chuyá»ƒn thÃ nh:
```java
T1 = load a
T2 = load b
T3 = T1 + T2
sum = T3
```
IR nÃ y giÃºp tá»‘i Æ°u hÃ³a dá»… dÃ ng hÆ¡n trÆ°á»›c khi táº¡o bytecode.
### **ğŸ”¹ Giai Ä‘oáº¡n 4: Sinh mÃ£ bytecode (Bytecode Generation)**

Sau khi cÃ³ IR, trÃ¬nh biÃªn dá»‹ch chuyá»ƒn Ä‘á»•i nÃ³ thÃ nh **bytecode**, lÃ  táº­p há»£p cÃ¡c **lá»‡nh mÃ¡y áº£o** cho JVM.  
VÃ­ dá»¥:
```java
public class Example {
    public static void main(String[] args) {
        int x = 5;
        int y = 10;
        int sum = x + y;
        System.out.println(sum);
    }
}
```
Bytecode (`javap -c Example.class`):
```java
0: iconst_5      // Push 5 lÃªn Stack
1: istore_1      // LÆ°u vÃ o biáº¿n x
2: iconst_10     // Push 10 lÃªn Stack
3: istore_2      // LÆ°u vÃ o biáº¿n y
4: iload_1       // Load x tá»« bá»™ nhá»›
5: iload_2       // Load y tá»« bá»™ nhá»›
6: iadd          // Cá»™ng x + y
7: istore_3      // LÆ°u káº¿t quáº£ vÃ o sum
8: getstatic java/lang/System.out
9: iload_3       // Load sum lÃªn Stack
10: invokevirtual java/io/PrintStream.println
```
## **2ï¸âƒ£ JVM xá»­ lÃ½ bytecode nhÆ° tháº¿ nÃ o?**

Khi cháº¡y lá»‡nh:
`java Example`

JVM thá»±c hiá»‡n 2 bÆ°á»›c:
### **ğŸ”¹ BÆ°á»›c 1: Kiá»ƒm tra mÃ£ bytecode (Bytecode Verification)**

TrÆ°á»›c khi cháº¡y, JVM kiá»ƒm tra:

- KhÃ´ng cÃ³ lá»‡nh bytecode báº¥t há»£p lá»‡.
- Táº¥t cáº£ biáº¿n Ä‘á»u Ä‘Æ°á»£c khá»Ÿi táº¡o trÆ°á»›c khi sá»­ dá»¥ng.
- KhÃ´ng truy cáº­p ngoÃ i vÃ¹ng nhá»›.

Náº¿u phÃ¡t hiá»‡n lá»—i, JVM bÃ¡o `java.lang.VerifyError`.

### **ğŸ”¹ BÆ°á»›c 2: Thá»±c thi mÃ£ bytecode**

CÃ³ 2 cÃ¡ch JVM thá»±c thi bytecode:

ğŸ”¸ **Interpreter** (Bá»™ thÃ´ng dá»‹ch):

- Äá»c tá»«ng lá»‡nh bytecode rá»“i thá»±c thi ngay.
- Nhanh trong khá»Ÿi Ä‘á»™ng nhÆ°ng cháº­m vá» lÃ¢u dÃ i.

ğŸ”¸ **JIT Compiler (Just-In-Time Compilation)**

- Chuyá»ƒn bytecode thÃ nh mÃ£ mÃ¡y ngay khi cáº§n.
- **HotSpot Compiler** tá»‘i Æ°u mÃ£ hay dÃ¹ng Ä‘á»ƒ tÄƒng tá»‘c.
- LÆ°u mÃ£ Ä‘Ã£ biÃªn dá»‹ch Ä‘á»ƒ dÃ¹ng láº¡i, giáº£m thá»i gian thá»±c thi.

VÃ­ dá»¥, náº¿u phÆ°Æ¡ng thá»©c `sum()` Ä‘Æ°á»£c gá»i nhiá»u láº§n, JIT sáº½ biÃªn dá»‹ch trá»±c tiáº¿p sang mÃ£ mÃ¡y Ä‘á»ƒ cháº¡y nhanh hÆ¡n.

## **3ï¸âƒ£ Káº¿t luáº­n**

âœ”ï¸ **BiÃªn dá»‹ch Java** gá»“m: Lexing, Parsing, Semantic Analysis, IR Generation, Bytecode Generation.  
âœ”ï¸ **Bytecode** giÃºp Java **Ä‘á»™c láº­p ná»n táº£ng** vÃ  **dá»… tá»‘i Æ°u hÃ³a**.  
âœ”ï¸ **JVM** thá»±c thi bytecode báº±ng **Interpreter** vÃ  **JIT Compiler** Ä‘á»ƒ cÃ¢n báº±ng tá»‘c Ä‘á»™ vÃ  hiá»‡u suáº¥t.